corella/__init__.py
corella/cli.py
corella-0.0.2.dist-info/METADATA
corella-0.0.2.dist-info/RECORD
corella-0.0.2.dist-info/WHEEL
corella-0.0.2.dist-info/entry_points.txt
corella-0.0.2.dist-info/top_level.txt
