Metadata-Version: 2.1
Name: corella
Version: 0.0.2
Summary: correlation matrix plots on the terminal
Home-page: http://github.com/nk412/corella
Author: Nagarjuna Kumarappan
Author-email: nagarjuna.412@gmail.com
License: MIT
Platform: UNKNOWN
Requires-Dist: pandas (>=0.23.4)
Requires-Dist: colored (>=1.3.93)
